froModuleDrivers/__init__.py
froModuleDrivers/agricultureDeviceDriver.py
froModuleDrivers/baseDriver.py
froModuleDrivers/conveyerBeltDriver.py
froModuleDrivers/gateway.py
froModuleDrivers/generalDeviceDriver.py
froModuleDrivers/homeDeviceDriver.py
froModuleDrivers/libraryDriver.py
froModuleDrivers/mCarDriver.py
froModuleDrivers/nioConnector.py
froModuleDrivers/nioManager.py
froModuleDrivers/protocol.py
froModuleDrivers/protocolHandler.py
froModuleDrivers/roboticArmDriver.py
froModuleDrivers/utils.py
froModuleDrivers-1.0.11.dist-info/LICENSE
froModuleDrivers-1.0.11.dist-info/METADATA
froModuleDrivers-1.0.11.dist-info/WHEEL
froModuleDrivers-1.0.11.dist-info/top_level.txt
froModuleDrivers-1.0.11.dist-info/RECORD
