Metadata-Version: 2.1
Name: froModuleDrivers
Version: 1.0.11
Summary: A package for easy use of fro net device application
Home-page: https://gitee.com/shaorong/fro-k12-python-driver.git
Author: roger
Author-email: mrshaorong@gmail.com
Classifier: Programming Language :: Python :: 3
Classifier: License :: OSI Approved :: MIT License
Classifier: Operating System :: OS Independent
Requires-Python: >=3.6
License-File: LICENSE
